odoo10_addon_web_widget_digitized_signature-10.0.0.1.0-py2.7-nspkg.pth
odoo/addons/web_widget_digitized_signature/README.rst
odoo/addons/web_widget_digitized_signature/__init__.py
odoo/addons/web_widget_digitized_signature/__manifest__.py
odoo/addons/web_widget_digitized_signature/i18n/ca.po
odoo/addons/web_widget_digitized_signature/i18n/es.po
odoo/addons/web_widget_digitized_signature/i18n/fr.po
odoo/addons/web_widget_digitized_signature/i18n/sl.po
odoo/addons/web_widget_digitized_signature/models/__init__.py
odoo/addons/web_widget_digitized_signature/models/mail_thread.py
odoo/addons/web_widget_digitized_signature/models/res_users.py
odoo/addons/web_widget_digitized_signature/static/description/icon.png
odoo/addons/web_widget_digitized_signature/static/lib/jSignature/jSignatureCustom.js
odoo/addons/web_widget_digitized_signature/static/src/js/digital_sign.js
odoo/addons/web_widget_digitized_signature/static/src/xml/digital_sign.xml
odoo/addons/web_widget_digitized_signature/tests/__init__.py
odoo/addons/web_widget_digitized_signature/tests/test_signature_tracking.py
odoo/addons/web_widget_digitized_signature/views/res_users_view.xml
odoo/addons/web_widget_digitized_signature/views/web_digital_sign_view.xml
odoo10_addon_web_widget_digitized_signature-10.0.0.1.0.dist-info/DESCRIPTION.rst
odoo10_addon_web_widget_digitized_signature-10.0.0.1.0.dist-info/METADATA
odoo10_addon_web_widget_digitized_signature-10.0.0.1.0.dist-info/RECORD
odoo10_addon_web_widget_digitized_signature-10.0.0.1.0.dist-info/WHEEL
odoo10_addon_web_widget_digitized_signature-10.0.0.1.0.dist-info/metadata.json
odoo10_addon_web_widget_digitized_signature-10.0.0.1.0.dist-info/namespace_packages.txt
odoo10_addon_web_widget_digitized_signature-10.0.0.1.0.dist-info/top_level.txt
